threadspipepy/__init__.py
threadspipepy/cli.py
threadspipepy/threadspipe.py
threadspipepy-0.4.4.dist-info/METADATA
threadspipepy-0.4.4.dist-info/WHEEL
threadspipepy-0.4.4.dist-info/entry_points.txt
threadspipepy-0.4.4.dist-info/licenses/LICENSE
threadspipepy-0.4.4.dist-info/RECORD
