Metadata-Version: 2.3
Name: threadspipepy
Version: 0.4.4
Summary: Python library for Threads by Instagram using the official Meta's Threads API
Project-URL: Homepage, https://github.com/paulosabayomi/ThreadsPipe-py
Project-URL: Issues, https://github.com/paulosabayomi/ThreadsPipe-py/issues
Author-email: Abayomi Amusa <amusapaulos99@gmail.com>
Maintainer-email: Abayomi Amusa <amusapaulos99@gmail.com>
License: MIT License
Keywords: library for instagram threads,library for threads,official threads API,official threads library,threads,threads api,threads library,threadspipe
Classifier: Operating System :: OS Independent
Classifier: Programming Language :: Python :: 3
Requires-Python: >=3.8
Requires-Dist: colorama
Requires-Dist: filetype
Requires-Dist: python-dotenv
Provides-Extra: cli
Requires-Dist: colorama; extra == 'cli'
